libmozdata/BZInfo.py
libmozdata/FXRevision.py
libmozdata/FileStats.py
libmozdata/HGFileInfo.py
libmozdata/__init__.py
libmozdata/bugzilla.py
libmozdata/buildhub.py
libmozdata/clouseau.py
libmozdata/config.py
libmozdata/connection.py
libmozdata/fx_trains.py
libmozdata/handler.py
libmozdata/hgmozilla.py
libmozdata/lando.py
libmozdata/modules.json
libmozdata/modules.py
libmozdata/patchanalysis.py
libmozdata/phabricator.py
libmozdata/redash.py
libmozdata/release_owners.py
libmozdata/socorro.py
libmozdata/utils.py
libmozdata/vcs_map.py
libmozdata/versions.py
libmozdata/wiki_parser.py
libmozdata-0.2.12.dist-info/LICENSE
libmozdata-0.2.12.dist-info/METADATA
libmozdata-0.2.12.dist-info/WHEEL
libmozdata-0.2.12.dist-info/top_level.txt
libmozdata-0.2.12.dist-info/RECORD
