Metadata-Version: 2.1
Name: libmozdata
Version: 0.2.12
Summary: Library to access and aggregate several Mozilla data sources.
Home-page: https://github.com/mozilla/libmozdata
Author: Mozilla Release Management
Author-email: release-mgmt@mozilla.com
License: MPL2
Platform: UNKNOWN
Classifier: Operating System :: OS Independent
Classifier: License :: OSI Approved :: Mozilla Public License 2.0 (MPL 2.0)
Classifier: Programming Language :: Python :: 3
Requires-Dist: icalendar (>=3.10)
Requires-Dist: python-dateutil (>=2.5.2)
Requires-Dist: python-hglib (>=2.6.1)
Requires-Dist: pytz (>=2022)
Requires-Dist: requests-futures (>=0.9.8)
Requires-Dist: requests[security] (>=2.7.0)
Requires-Dist: setuptools (>=28.6.1)
Requires-Dist: six (>=1.10.0)
Requires-Dist: whatthepatch (>=0.0.4)
